directord/__init__.py
directord/bootstrap.py
directord/client.py
directord/interface.py
directord/iodict.py
directord/logger.py
directord/main.py
directord/meta.py
directord/mixin.py
directord/models.py
directord/server.py
directord/user.py
directord/utils.py
directord/components/__init__.py
directord/components/builtin_add.py
directord/components/builtin_arg.py
directord/components/builtin_cacheevict.py
directord/components/builtin_cachefile.py
directord/components/builtin_copy.py
directord/components/builtin_dnf.py
directord/components/builtin_env.py
directord/components/builtin_query.py
directord/components/builtin_queuesentinel.py
directord/components/builtin_run.py
directord/components/builtin_service.py
directord/components/builtin_wait.py
directord/components/builtin_workdir.py
directord/components/lib/__init__.py
directord/components/lib/podman.py
directord/datastores/__init__.py
directord/datastores/disc.py
directord/datastores/memory.py
directord/datastores/redis.py
directord/drivers/__init__.py
directord/drivers/dummy.py
directord/drivers/grpcd.py
directord/drivers/messaging.py
directord/drivers/zeromq.py
directord/drivers/generated/__init__.py
directord/drivers/generated/msg.proto
directord/drivers/generated/msg_pb2.py
directord/drivers/generated/msg_pb2_grpc.py
directord/templates/directord-client.service.j2
directord/templates/directord-server.service.j2
directord/templates/robots.txt
directord-0.12.0.data/data/share/directord/components/container_config_data.py
directord-0.12.0.data/data/share/directord/components/container_image.py
directord-0.12.0.data/data/share/directord/components/echo.py
directord-0.12.0.data/data/share/directord/components/facter.py
directord-0.12.0.data/data/share/directord/components/job_wait.py
directord-0.12.0.data/data/share/directord/components/pod.py
directord-0.12.0.data/data/share/directord/components/query_wait.py
directord-0.12.0.data/data/share/directord/components/reboot.py
directord-0.12.0.dist-info/LICENSE
directord-0.12.0.dist-info/METADATA
directord-0.12.0.dist-info/WHEEL
directord-0.12.0.dist-info/entry_points.txt
directord-0.12.0.dist-info/top_level.txt
directord-0.12.0.dist-info/RECORD
