Metadata-Version: 2.1
Name: directord
Version: 0.12.0
Summary: A deployment framework built to manage the data center life cycle.
Home-page: https://github.com/directord/directord
Author: Kevin Carter
Author-email: kevin@cloudnull.com
License: UNKNOWN
Project-URL: Bug Tracker, https://github.com/directord/directord/issues
Platform: UNKNOWN
Classifier: Development Status :: 5 - Production/Stable
Classifier: Intended Audience :: Information Technology
Classifier: Intended Audience :: System Administrators
Classifier: Intended Audience :: Developers
Classifier: Operating System :: OS Independent
Classifier: Programming Language :: Python :: 3.8
Classifier: Topic :: Utilities
Classifier: Topic :: Software Development :: Libraries :: Python Modules
Requires-Python: >=3.6
License-File: LICENSE
Requires-Dist: jinja2
Requires-Dist: pyyaml
Requires-Dist: requests
Requires-Dist: ssh-python
Requires-Dist: tabulate
Requires-Dist: tenacity
Provides-Extra: all
Requires-Dist: grpcio-tools (<=1.26.0) ; extra == 'all'
Requires-Dist: oslo-messaging[amqp1] ; extra == 'all'
Requires-Dist: coverage ; extra == 'all'
Requires-Dist: redis ; extra == 'all'
Requires-Dist: protobuf ; extra == 'all'
Requires-Dist: flake8 ; extra == 'all'
Requires-Dist: podman-py ; extra == 'all'
Requires-Dist: pyzmq ; extra == 'all'
Provides-Extra: dev
Requires-Dist: podman-py ; extra == 'dev'
Requires-Dist: grpcio-tools (<=1.26.0) ; extra == 'dev'
Provides-Extra: grpc
Requires-Dist: grpcio-tools (<=1.26.0) ; extra == 'grpc'
Requires-Dist: protobuf ; extra == 'grpc'
Provides-Extra: oslo_messaging
Requires-Dist: oslo-messaging[amqp1] ; extra == 'oslo_messaging'
Provides-Extra: redis
Requires-Dist: redis ; extra == 'redis'
Provides-Extra: test
Requires-Dist: flake8 ; extra == 'test'
Requires-Dist: coverage ; extra == 'test'
Provides-Extra: zmq
Requires-Dist: pyzmq ; extra == 'zmq'
